synchronisers/design.v
module des(
    input sys_clk,
    input p_clk,
    input q_clk,
    output PeqQ,
    output PleQ,
    output PgrQ
);

reg p_sync, q_sync;
reg p_sync2, q_sync2;
reg p_sync3, q_sync3;
reg p_rise, q_rise;

// Edge detection
always @(posedge sys_clk) begin
  p_sync  <= p_clk;
  p_sync2 <= p_sync;
  p_sync3 <= p_sync2;
  p_rise  <= ~p_sync3 & p_sync2;

  q_sync  <= q_clk;
  q_sync2 <= q_sync;
  q_sync3 <= q_sync2;
  q_rise  <= ~q_sync3 & q_sync2;
end

// Period counters
reg [7:0] period_p = 0;
reg [7:0] period_q = 0;

always @(posedge sys_clk) begin
  if (p_rise)
    period_p <= 0;
  else
    period_p <= period_p + 1;

  if (q_rise)
    period_q <= 0;
  else
    period_q <= period_q + 1;
end

// Output comparison
assign PeqQ = (period_p == period_q);
assign PgrQ = (period_p >  period_q);
assign PleQ = (period_p <  period_q);

endmodule

synchronisers/tb.v
module tb();

reg sys_clk, p_clk, q_clk;
wire PeqQ, PleQ, PgrQ;

des uut (.sys_clk(sys_clk),
            .p_clk(p_clk),
            .q_clk(q_clk),
            .PeqQ(PeqQ),
            .PleQ(PleQ),
            .PgrQ(PgrQ)
            );


always #5 sys_clk = ~sys_clk;

always #10 p_clk = ~p_clk;

always #10 q_clk = ~q_clk;

initial begin
  $dumpfile("test.vcd");
  $dumpvars(0, tb);

  sys_clk = 0;

  p_clk = 0;

  q_clk = 1;


  #500

  $finish;
end
endmodule

synchronisers/test.vcd
$date
	Sun Jul 13 21:02:23 2025
$end
$version
	Icarus Verilog
$end
$timescale
	1s
$end
$scope module tb $end
$var wire 1 ! PleQ $end
$var wire 1 " PgrQ $end
$var wire 1 # PeqQ $end
$var reg 1 $ p_clk $end
$var reg 1 % q_clk $end
$var reg 1 & sys_clk $end
$scope module uut $end
$var wire 1 $ p_clk $end
$var wire 1 % q_clk $end
$var wire 1 & sys_clk $end
$var wire 1 ! PleQ $end
$var wire 1 " PgrQ $end
$var wire 1 # PeqQ $end
$var reg 1 ' p_rise $end
$var reg 1 ( p_sync $end
$var reg 1 ) p_sync2 $end
$var reg 1 * p_sync3 $end
$var reg 8 + period_p [7:0] $end
$var reg 8 , period_q [7:0] $end
$var reg 1 - q_rise $end
$var reg 1 . q_sync $end
$var reg 1 / q_sync2 $end
$var reg 1 0 q_sync3 $end
$upscope $end
$upscope $end
$enddefinitions $end
#0
$dumpvars
x0
x/
x.
x-
b0 ,
b0 +
x*
x)
x(
x'
0&
1%
0$
1#
0"
0!
$end
#5
1.
0(
b1 ,
1#
0"
b1 +
1&
#10
0&
0%
1$
#15
b10 ,
1#
0"
b10 +
1/
0.
0)
1(
1&
#20
0&
1%
0$
#25
10
0/
1.
0'
0*
1)
0(
b11 ,
1#
0"
b11 +
1&
#30
0&
0%
1$
#35
b100 ,
1#
0"
b100 +
0-
00
1/
0.
1'
1*
0)
1(
1&
#40
0&
1%
0$
#45
1-
10
0/
1.
0'
0*
1)
0(
b101 ,
0#
1!
b0 +
1&
#50
0&
0%
1$
#55
1"
0!
b0 ,
b1 +
0-
00
1/
0.
1'
1*
0)
1(
1&
#60
0&
1%
0$
#65
1-
10
0/
1.
0'
0*
1)
0(
1!
b1 ,
0#
0"
b0 +
1&
#70
0&
0%
1$
#75
1"
b0 ,
0#
0!
b1 +
0-
00
1/
0.
1'
1*
0)
1(
1&
#80
0&
1%
0$
#85
1-
10
0/
1.
0'
0*
1)
0(
1!
b1 ,
0#
0"
b0 +
1&
#90
0&
0%
1$
#95
1"
b0 ,
0#
0!
b1 +
0-
00
1/
0.
1'
1*
0)
1(
1&
#100
0&
1%
0$
#105
1-
10
0/
1.
0'
0*
1)
0(
1!
b1 ,
0#
0"
b0 +
1&
#110
0&
0%
1$
#115
1"
b0 ,
0#
0!
b1 +
0-
00
1/
0.
1'
1*
0)
1(
1&
#120
0&
1%
0$
#125
1-
10
0/
1.
0'
0*
1)
0(
1!
b1 ,
0#
0"
b0 +
1&
#130
0&
0%
1$
#135
1"
b0 ,
0#
0!
b1 +
0-
00
1/
0.
1'
1*
0)
1(
1&
#140
0&
1%
0$
#145
1-
10
0/
1.
0'
0*
1)
0(
1!
b1 ,
0#
0"
b0 +
1&
#150
0&
0%
1$
#155
1"
b0 ,
0#
0!
b1 +
0-
00
1/
0.
1'
1*
0)
1(
1&
#160
0&
1%
0$
#165
1-
10
0/
1.
0'
0*
1)
0(
1!
b1 ,
0#
0"
b0 +
1&
#170
0&
0%
1$
#175
1"
b0 ,
0#
0!
b1 +
0-
00
1/
0.
1'
1*
0)
1(
1&
#180
0&
1%
0$
#185
1-
10
0/
1.
0'
0*
1)
0(
1!
b1 ,
0#
0"
b0 +
1&
#190
0&
0%
1$
#195
1"
b0 ,
0#
0!
b1 +
0-
00
1/
0.
1'
1*
0)
1(
1&
#200
0&
1%
0$
#205
1-
10
0/
1.
0'
0*
1)
0(
1!
b1 ,
0#
0"
b0 +
1&
#210
0&
0%
1$
#215
1"
b0 ,
0#
0!
b1 +
0-
00
1/
0.
1'
1*
0)
1(
1&
#220
0&
1%
0$
#225
1-
10
0/
1.
0'
0*
1)
0(
1!
b1 ,
0#
0"
b0 +
1&
#230
0&
0%
1$
#235
1"
b0 ,
0#
0!
b1 +
0-
00
1/
0.
1'
1*
0)
1(
1&
#240
0&
1%
0$
#245
1-
10
0/
1.
0'
0*
1)
0(
1!
b1 ,
0#
0"
b0 +
1&
#250
0&
0%
1$
#255
1"
b0 ,
0#
0!
b1 +
0-
00
1/
0.
1'
1*
0)
1(
1&
#260
0&
1%
0$
#265
1-
10
0/
1.
0'
0*
1)
0(
1!
b1 ,
0#
0"
b0 +
1&
#270
0&
0%
1$
#275
1"
b0 ,
0#
0!
b1 +
0-
00
1/
0.
1'
1*
0)
1(
1&
#280
0&
1%
0$
#285
1-
10
0/
1.
0'
0*
1)
0(
1!
b1 ,
0#
0"
b0 +
1&
#290
0&
0%
1$
#295
1"
b0 ,
0#
0!
b1 +
0-
00
1/
0.
1'
1*
0)
1(
1&
#300
0&
1%
0$
#305
1-
10
0/
1.
0'
0*
1)
0(
1!
b1 ,
0#
0"
b0 +
1&
#310
0&
0%
1$
#315
1"
b0 ,
0#
0!
b1 +
0-
00
1/
0.
1'
1*
0)
1(
1&
#320
0&
1%
0$
#325
1-
10
0/
1.
0'
0*
1)
0(
1!
b1 ,
0#
0"
b0 +
1&
#330
0&
0%
1$
#335
1"
b0 ,
0#
0!
b1 +
0-
00
1/
0.
1'
1*
0)
1(
1&
#340
0&
1%
0$
#345
1-
10
0/
1.
0'
0*
1)
0(
1!
b1 ,
0#
0"
b0 +
1&
#350
0&
0%
1$
#355
1"
b0 ,
0#
0!
b1 +
0-
00
1/
0.
1'
1*
0)
1(
1&
#360
0&
1%
0$
#365
1-
10
0/
1.
0'
0*
1)
0(
1!
b1 ,
0#
0"
b0 +
1&
#370
0&
0%
1$
#375
1"
b0 ,
0#
0!
b1 +
0-
00
1/
0.
1'
1*
0)
1(
1&
#380
0&
1%
0$
#385
1-
10
0/
1.
0'
0*
1)
0(
1!
b1 ,
0#
0"
b0 +
1&
#390
0&
0%
1$
#395
1"
b0 ,
0#
0!
b1 +
0-
00
1/
0.
1'
1*
0)
1(
1&
#400
0&
1%
0$
#405
1-
10
0/
1.
0'
0*
1)
0(
1!
b1 ,
0#
0"
b0 +
1&
#410
0&
0%
1$
#415
1"
b0 ,
0#
0!
b1 +
0-
00
1/
0.
1'
1*
0)
1(
1&
#420
0&
1%
0$
#425
1-
10
0/
1.
0'
0*
1)
0(
1!
b1 ,
0#
0"
b0 +
1&
#430
0&
0%
1$
#435
1"
b0 ,
0#
0!
b1 +
0-
00
1/
0.
1'
1*
0)
1(
1&
#440
0&
1%
0$
#445
1-
10
0/
1.
0'
0*
1)
0(
1!
b1 ,
0#
0"
b0 +
1&
#450
0&
0%
1$
#455
1"
b0 ,
0#
0!
b1 +
0-
00
1/
0.
1'
1*
0)
1(
1&
#460
0&
1%
0$
#465
1-
10
0/
1.
0'
0*
1)
0(
1!
b1 ,
0#
0"
b0 +
1&
#470
0&
0%
1$
#475
1"
b0 ,
0#
0!
b1 +
0-
00
1/
0.
1'
1*
0)
1(
1&
#480
0&
1%
0$
#485
1-
10
0/
1.
0'
0*
1)
0(
1!
b1 ,
0#
0"
b0 +
1&
#490
0&
0%
1$
#495
1"
b0 ,
0#
0!
b1 +
0-
00
1/
0.
1'
1*
0)
1(
1&
