div_3/design.v
module three(
  input clk,
  input reset,
  input bit,
  output out
);

parameter S0 = 2'b00, S1 = 2'b01, S2 = 2'b10;
reg [1:0] state, n_state;
always @(*) begin
  case (state)
    S0: n_state = (bit) ? S1 : S0;
    S1: n_state = (bit) ? S0 : S2;
    S2: n_state = (bit) ? S2 : S1;
    default :  n_state = S0;
  endcase
end

always @(posedge clk) begin
  if(reset) state <= S0;
  else state <= n_state;
end

assign out = (state == S0);

endmodule

div_3/tb.v
module tb();

reg clk, reset;
reg n;
wire out;

three uut(
    .clk(clk),
    .reset(reset),
    .bit(n),
    .out(out)
);

always #5 clk = ~clk;

reg exp;

initial begin
  $dumpfile("test.vcd");
  $dumpvars(0, tb);

  clk = 0;
  reset = 1;
  n = 0;         // Initialize input
  #10 reset = 0;

  // Test 1
  #10 n = 1;
  #10 n = 1;
  #10;
  exp = 1;
  #1;
  if (out == exp)
    $display("PASS: out = %b, expected = %b", out, exp);
  else
    $display("FAIL: out = %b, expected = %b", out, exp);

  // Reset before next test
  reset = 1;
  n = 0;
  #10 reset = 0;

  // Test 2
  #10 n = 0;
  #10 n = 1;
  #10 n = 1;
  #10 n = 0;
  #10
  exp = 1;
  #10
  if (out == exp)
    $display("PASS: out = %b, expected = %b", out, exp);
  else
    $display("FAIL: out = %b, expected = %b", out, exp);

  #10 $finish;
end

endmodule

div_3/test.vcd
$date
	Sun Jul 13 21:36:06 2025
$end
$version
	Icarus Verilog
$end
$timescale
	1s
$end
$scope module tb $end
$var wire 1 ! out $end
$var reg 1 " clk $end
$var reg 1 # exp $end
$var reg 1 $ n $end
$var reg 1 % reset $end
$scope module uut $end
$var wire 1 $ bit $end
$var wire 1 " clk $end
$var wire 1 % reset $end
$var wire 1 ! out $end
$var reg 2 & n_state [1:0] $end
$var reg 2 ' state [1:0] $end
$upscope $end
$upscope $end
$enddefinitions $end
#0
$dumpvars
bx '
b0 &
1%
0$
x#
0"
x!
$end
#5
1!
b0 '
1"
#10
0"
0%
#15
1"
#20
b1 &
0"
1$
#25
b0 &
0!
b1 '
1"
#30
0"
#35
b1 &
1!
b0 '
1"
#40
0"
1#
#41
b0 &
0$
1%
#45
1"
#50
0"
#51
0%
#55
1"
#60
0"
#65
1"
#70
0"
#71
b1 &
1$
#75
b0 &
0!
b1 '
1"
#80
0"
#85
b1 &
1!
b0 '
1"
#90
0"
#91
b0 &
0$
