counter/d_ff.v
module d_ff(
    input D, clk, rst,
    output reg Q
);

always @(posedge clk) begin
  if(rst)
    Q <= 0;
  else Q <= D;
end

endmodule

counter/counter.v
module counter(
    input clk, rst, e,
    output wire A0, A1, A2, A3
);
wire y;
assign y = A3 & A1;

d_ff ff_0(.clk(clk & e), .rst(y|rst), .D(~A0), .Q(A0));
d_ff ff_1(.clk(~A0 & e), .rst(y|rst), .D(~A1), .Q(A1));
d_ff ff_2(.clk(~A1 & e), .rst(y|rst), .D(~A2), .Q(A2));
d_ff ff_3(.clk(~A2 & e), .rst(y|rst), .D(~A3), .Q(A3));



endmodule

counter/counter_tb.v
module counter_tb();
//input 
reg clk, rst, e;

//output 
wire A0, A1, A2, A3;

counter uut(
    .clk(clk),
    .rst(rst),
    .A0(A0),
    .A1(A1),
    .A2(A2),
    .A3(A3),
    .e(e)
);
always #5 clk = ~clk;

initial begin
  $monitor("time= %t  A3 = %b  A2 = %b  A1= %b  A0 = %b", $time, A3, A2, A1, A0);
  $dumpfile("test.vcd");
  $dumpvars(0, counter_tb);

  clk = 0;
  rst = 1;
    e= 1;
  #10 rst = 0;

  #500;
  e=0;
  $finish;
end

endmodule

counter/test.vcd
$date
	Sun Mar 23 11:38:02 2025
$end
$version
	Icarus Verilog
$end
$timescale
	1s
$end
$scope module counter_tb $end
$var wire 1 ! A3 $end
$var wire 1 " A2 $end
$var wire 1 # A1 $end
$var wire 1 $ A0 $end
$var reg 1 % clk $end
$var reg 1 & e $end
$var reg 1 ' rst $end
$scope module uut $end
$var wire 1 % clk $end
$var wire 1 & e $end
$var wire 1 ' rst $end
$var wire 1 ( y $end
$var wire 1 ! A3 $end
$var wire 1 " A2 $end
$var wire 1 # A1 $end
$var wire 1 $ A0 $end
$scope module ff_0 $end
$var wire 1 ) D $end
$var wire 1 * clk $end
$var wire 1 + rst $end
$var reg 1 $ Q $end
$upscope $end
$scope module ff_1 $end
$var wire 1 , D $end
$var wire 1 - clk $end
$var wire 1 . rst $end
$var reg 1 # Q $end
$upscope $end
$scope module ff_2 $end
$var wire 1 / D $end
$var wire 1 0 clk $end
$var wire 1 1 rst $end
$var reg 1 " Q $end
$upscope $end
$scope module ff_3 $end
$var wire 1 2 D $end
$var wire 1 3 clk $end
$var wire 1 4 rst $end
$var reg 1 ! Q $end
$upscope $end
$upscope $end
$upscope $end
$enddefinitions $end
#0
$dumpvars
14
x3
x2
11
x0
x/
1.
x-
x,
1+
0*
x)
x(
1'
1&
0%
x$
x#
x"
x!
$end
#5
12
0!
13
1/
0"
10
1,
0(
0#
1-
1)
0$
1*
1%
#10
0*
0+
0.
01
04
0%
0'
#15
0-
0)
1$
1*
1%
#20
0*
0%
#25
00
0,
1#
1-
1)
0$
1*
1%
#30
0*
0%
#35
0-
0)
1$
1*
1%
#40
0*
0%
#45
03
0/
1"
10
1,
0#
1-
1)
0$
1*
1%
#50
0*
0%
#55
0-
0)
1$
1*
1%
#60
0*
0%
#65
00
0,
1#
1-
1)
0$
1*
1%
#70
0*
0%
#75
0-
0)
1$
1*
1%
#80
0*
0%
#85
02
1!
13
1/
0"
10
1,
0#
1-
1)
0$
1*
1%
#90
0*
0%
#95
0-
0)
1$
1*
1%
#100
0*
0%
#105
00
1+
1.
11
14
0,
1(
1#
1-
1)
0$
1*
1%
