2complFSM/design.v
module FSM(
    input a,
    input clk,
    input reset,
    output reg y
);

reg A, B;
reg A_in, B_in;
always @(posedge clk) begin
  if (reset) begin
    A <= 0;
    B <= 0;
  end else begin  
    A_in = A;
    B_in = B;
    A <= B_in + A_in;
    B <= a;
  end
  
end

always @(posedge clk) begin
 y = (B & (~a)) | (A & (~a)) | (a & (~A) & (~B));
end

endmodule

2complFSM/testbench.v
module FSM_tb();

reg a;
reg clk;
reg reset;
wire y;

FSM uut(.a(a), .y(y), .clk(clk), .reset(reset));

always #5 clk = ~clk;

initial begin

$monitor("x= %b , y = %b", a, y);
$dumpfile("test.vcd");
$dumpvars(0, FSM_tb);
  clk = 0;
  reset = 1;
  #10 reset = 0;

  a = 0; #10;
  a = 0; #10;
  a = 0; #10;
  a = 1; #10;
  a = 1; #10;

  reset = 1; #10;
  reset = 0; #10;

  a = 0; #10;
  a = 1; #10;
  a = 0; #10;
  a = 1; #10;
  a = 0; #10;
  a = 1; #10;

$finish;

end

endmodule

2complFSM/test.vcd
$date
	Wed Jun 18 22:24:46 2025
$end
$version
	Icarus Verilog
$end
$timescale
	1s
$end
$scope module FSM_tb $end
$var wire 1 ! y $end
$var reg 1 " a $end
$var reg 1 # clk $end
$var reg 1 $ reset $end
$scope module uut $end
$var wire 1 " a $end
$var wire 1 # clk $end
$var wire 1 $ reset $end
$var reg 1 % A $end
$var reg 1 & A_in $end
$var reg 1 ' B $end
$var reg 1 ( B_in $end
$var reg 1 ! y $end
$upscope $end
$upscope $end
$enddefinitions $end
#0
$dumpvars
x(
x'
x&
x%
1$
0#
x"
x!
$end
#5
0'
0%
1#
#10
0#
0"
0$
#15
0!
0(
0&
1#
#20
0#
#25
1#
#30
0#
#35
1#
#40
0#
1"
#45
1'
1!
1#
#50
0#
#55
1%
0!
1(
1#
#60
0#
1$
#65
0'
0%
1#
#70
0#
0$
#75
1'
1!
0(
1#
#80
0#
0"
#85
0'
1%
1(
1#
#90
0#
1"
#95
1'
0!
0(
1&
1#
#100
0#
0"
#105
0'
0%
1(
1!
1#
#110
0#
1"
#115
1'
0(
0&
1#
#120
0#
0"
#125
0'
1%
1(
1#
#130
0#
1"
#135
1'
0!
0(
1&
1#
